{
  "MSG_LOG_ALM_1_1000": "Initiating framework.",
  "MSG_LOG_ALM_1_1001": "Framework intialization failed.",
  "MSG_LOG_ALM_1_1002": "Closing framework.",
  "MSG_LOG_ALM_1_1003": "Initiating system setup task.",
  "MSG_LOG_ALM_1_1004": "Initiating user operation task.",
  "MSG_LOG_ALM_1_1005": "Initiating equipment task.",
  "MSG_LOG_ALM_1_1006": "Initiating algorithm task.",
  "MSG_LOG_ALM_1_1007": "Closing algorithm task.",
  "MSG_LOG_ALM_1_1008": "Closing equipment task.",
  "MSG_LOG_ALM_1_1009": "Closing user operation task.",
  "MSG_LOG_ALM_1_1010": "Closing system setup task.",
  "MSG_LOG_ALM_1_1011": "Executing system shutdown command.",
  "MSG_LOG_ALM_1_1012": "Executing system restart command.",
  "MSG_LOG_ALM_1_1013": "Changing system time setup.",
  "MSG_LOG_ALM_1_1014": "Changing system IP address setup.",
  "MSG_LOG_ALM_1_1015": "System setup command not supported.",
  "MSG_LOG_ALM_1_1016": "Saving new system environment file.",
  "MSG_LOG_ALM_1_1017": "No saved system environment file.",
  "MSG_LOG_ALM_1_1018": "System status changed.",
  "MSG_LOG_ALM_1_1019": "3 Postion Enable Switch should be in the centre enabled position for robot operation. 3 Position Enable switch should be released and re-enabled after servo-off or mode change.",
  "MSG_LOG_ALM_1_1020": "Encoder initialization has been completed.",
  "MSG_LOG_ALM_1_1021": "No TCP info with the same name.",
  "MSG_LOG_ALM_1_1022": "No tool info with the same name.",
  "MSG_LOG_ALM_1_1023": "External Safe Torque Off signal entered.",
  "MSG_LOG_ALM_1_1024": "External Emergency Stop signal entered.",
  "MSG_LOG_ALM_1_1025": "External Protective Stop signal entered.",
  "MSG_LOG_ALM_1_1026": "External Deceleration Mode signal entered.",
  "MSG_LOG_ALM_1_1027": "Unable to stop collision detection mode.",
  "MSG_LOG_ALM_1_1028": "Restarts Collision detection mode.",
  "MSG_LOG_ALM_1_1029": "Starts recovery mode.",
  "MSG_LOG_ALM_1_1030": "Could not find environment file name.",
  "MSG_LOG_ALM_1_1031": "Maximum number of tools that can be saved has been exceeded.",
  "MSG_LOG_ALM_1_1032": "Maximum number of TCPs that can be saved has been exceeded.",
  "MSG_LOG_ALM_1_1033": "Cannot change the tool settings outside the specified area.",
  "MSG_LOG_ALM_1_1034": "Cannot change the TCP settings outside the specified area.",
  "MSG_LOG_ALM_1_1035": "External Direct Teach Mode signal entered.",
  "MSG_LOG_ALM_1_1036": "External Manual Guide Stop signal entered.",
  "MSG_LOG_ALM_1_1037": "The mastering operation may be required to improve repetition accuracy",
  "MSG_LOG_ALM_1_1038": "For safety reasons, the state of robot was changed to safe-off after a specified period of inactivity.",
  "MSG_LOG_ALM_1_1039": "External Protective Stop Auto Resume signal entered.",
  "MSG_LOG_ALM_1_1040": "External Remote I/O Control Mode Signal entered.",
  "MSG_LOG_ALM_1_1041": "You do not have permission to set up and control robot",
  "MSG_LOG_ALM_1_1042": "The remote I / O control mode is not activated.",
  "MSG_LOG_ALM_1_1043": "Two or more remote I / O control signals have been input",
  "MSG_LOG_ALM_1_1044": "The remote I / O control signal has been input.",
  "MSG_LOG_ALM_1_1045": "The remote I / O control signal was ignored.",
  "MSG_LOG_ALM_1_1046": "External Remote I/O Control Mode Signal is cleared",
  "MSG_LOG_ALM_1_1047": "User home settings cannot be changed because the current robot position and setup position are different",
  "MSG_LOG_ALM_1_1049": "Before the next Handguiding, all Handguiding related switches and signals should be released",
  "MSG_LOG_ALM_1_1050": "External Error Reset &amp; Resume signal has been input.",
  "MSG_LOG_ALM_1_1051": "External Reset signal has been input.",
  "MSG_LOG_ALM_1_1052": "Dedicated Protective Stop signal entered.",
  "MSG_LOG_ALM_1_1053": "The Power On signal is entered.",
  "MSG_LOG_ALM_1_1054": "The Power Off signal is entered.",
  "MSG_LOG_ALM_1_2000": "Saving program as default mode.",
  "MSG_LOG_ALM_1_2001": "Deleting default program.",
  "MSG_LOG_ALM_1_2002": "Executing program.",
  "MSG_LOG_ALM_1_2003": "Program already running.",
  "MSG_LOG_ALM_1_2004": "Stopping program execution.",
  "MSG_LOG_ALM_1_2005": "Pausing program execution.",
  "MSG_LOG_ALM_1_2006": "Resuming program.",
  "MSG_LOG_ALM_1_2007": "Program closed (normal closing).",
  "MSG_LOG_ALM_1_2008": "Program closed (forced closing).",
  "MSG_LOG_ALM_1_2009": "Program closed (internal error closing).",
  "MSG_LOG_ALM_1_2010": "SW error occurred.",
  "MSG_LOG_ALM_1_2011": "Internal error occurred.",
  "MSG_LOG_ALM_1_2012": "Interpreter initialization error occurred.",
  "MSG_LOG_ALM_1_2013": "Executing program file is empty.",
  "MSG_LOG_ALM_1_2014": "Error occurred during program grammar error check.",
  "MSG_LOG_ALM_1_2015": "Program grammar error occurred.",
  "MSG_LOG_ALM_1_2016": "DRL Type error occurred during program execution.",
  "MSG_LOG_ALM_1_2017": "DRL Value error occurred during program execution.",
  "MSG_LOG_ALM_1_2018": "DRL Runtime error occurred during program execution.",
  "MSG_LOG_ALM_1_2019": "Python Runtime error occurred during program execution.",
  "MSG_LOG_ALM_1_2021": "This DRL command is not available for this Flange Board.\r\nCommand: {{0}}",
  "MSG_LOG_ALM_1_2022": "This DRL command is only supported on RS485.\r\nCommand: {{0}}",
  "MSG_LOG_ALM_1_3000": "Initiating server for T/P.",
  "MSG_LOG_ALM_1_3001": "Closing server for T/P.",
  "MSG_LOG_ALM_1_3002": "Client T/P connected.",
  "MSG_LOG_ALM_1_3003": "Client T/P disconnected.",
  "MSG_LOG_ALM_1_3004": "Client T/P authentication failed.",
  "MSG_LOG_ALM_1_3005": "Unauthorized equipment ID number.",
  "MSG_LOG_ALM_1_3006": "Client T/P transmission buffer overflow occurred.",
  "MSG_LOG_ALM_1_3007": "Error occurred during data transmission to client T/P.",
  "MSG_LOG_ALM_1_3008": "You can not get an IP from the DHCP server.",
  "MSG_LOG_ALM_1_3009": "Client T/P received buffer overflow occurred.",
  "MSG_LOG_ALM_1_3010": "Failed to connect to KT server.",
  "MSG_LOG_ALM_1_3011": "Authentication to KT sever failed.",
  "MSG_LOG_ALM_1_3012": "Setting is unavailable due to the disabled network.",
  "MSG_LOG_ALM_1_3013": "A notification occurred during real-time external control.\r\nDetailed causes: {{0}}",
  "MSG_LOG_ALM_1_3014": "An error occurred during real-time external control.",
  "MSG_LOG_ALM_1_4000": "EtherCAT Master initialization failed.",
  "MSG_LOG_ALM_1_4001": "Invalid Slave type.",
  "MSG_LOG_ALM_1_4002": "JobTask creation and initialization failed.",
  "MSG_LOG_ALM_1_4003": "Invalid ENI file.",
  "MSG_LOG_ALM_1_4004": "Device does not support DC Sync.",
  "MSG_LOG_ALM_1_4005": "DC Sync initialization failed.",
  "MSG_LOG_ALM_1_4006": "Notify Callback function registration failed.",
  "MSG_LOG_ALM_1_4007": "Invalid Vendor ID or Product Code.",
  "MSG_LOG_ALM_1_4008": "INIT state change failed.",
  "MSG_LOG_ALM_1_4009": "PREOP state change failed.",
  "MSG_LOG_ALM_1_4010": "Slave device initialization failed.",
  "MSG_LOG_ALM_1_4011": "PDO communication initialization failed.",
  "MSG_LOG_ALM_1_4012": "SAFEOP state change failed.",
  "MSG_LOG_ALM_1_4013": "DCM state acquisition failed.",
  "MSG_LOG_ALM_1_4014": "OP state change failed.",
  "MSG_LOG_ALM_1_4015": "Stop Master failed.",
  "MSG_LOG_ALM_1_4016": "Notify Callback function release failed.",
  "MSG_LOG_ALM_1_4017": "Master Release failed.",
  "MSG_LOG_ALM_1_4018": "BOOTSTRAP state change failed.",
  "MSG_LOG_ALM_1_4019": "Open update file failed.",
  "MSG_LOG_ALM_1_4020": "Inverter update failed.",
  "MSG_LOG_ALM_1_4021": "Invalid update file.",
  "MSG_LOG_ALM_1_4022": "RX frame receive failed.",
  "MSG_LOG_ALM_1_4023": "Cycle frame transmission failed.",
  "MSG_LOG_ALM_1_4024": "DC Sync failed.",
  "MSG_LOG_ALM_1_4025": "Async Cycle frame transmission failed.",
  "MSG_LOG_ALM_1_4026": "Error occurred.",
  "MSG_LOG_ALM_1_5000": "Interface board connection successful.",
  "MSG_LOG_ALM_1_5001": "Interface board connection failed.",
  "MSG_LOG_ALM_1_5002": "Interface board connection closed.",
  "MSG_LOG_ALM_1_5003": "Error occurred during reading.",
  "MSG_LOG_ALM_1_5004": "Error occurred during writing.",
  "MSG_LOG_ALM_1_5005": "CRC error occurred during reading.",
  "MSG_LOG_ALM_1_5006": "Protocol (command) not supported.",
  "MSG_LOG_ALM_1_5007": "Digital output changed.",
  "MSG_LOG_ALM_1_5008": "Analog output changed.",
  "MSG_LOG_ALM_1_5009": "Safety output changed.",
  "MSG_LOG_ALM_1_5010": "Analog input type changed.",
  "MSG_LOG_ALM_1_5011": "Analog output type changed.",
  "MSG_LOG_ALM_1_5012": "Data input cycle changed.",
  "MSG_LOG_ALM_1_5013": "I/O input range exceeded.",
  "MSG_LOG_ALM_1_5014": "Sequence number error occurred during reading.",
  "MSG_LOG_ALM_1_6000": "Modbus equipment connection successful.",
  "MSG_LOG_ALM_1_6001": "Modbus equipment connection failed.",
  "MSG_LOG_ALM_1_6002": "Modbus I/O variable added.",
  "MSG_LOG_ALM_1_6003": "Variable already exists on designated register address.",
  "MSG_LOG_ALM_1_6004": "Modbus I/O variable adding failed.",
  "MSG_LOG_ALM_1_6005": "Modbus I/O variable deleted.",
  "MSG_LOG_ALM_1_6006": "No I/O variable with designated name.",
  "MSG_LOG_ALM_1_6007": "Modbus I/O variable output changed.",
  "MSG_LOG_ALM_1_6008": "Modbus I/O variable deletion failed.",
  "MSG_LOG_ALM_1_6009": "Modbus I/O variable output failed.",
  "MSG_LOG_ALM_1_6010": "Maximum number of Modbus slave that can be saved has been exceeded.",
  "MSG_LOG_ALM_1_6011": "Maximum number of register that can be saved per modbus slave has been exceeded.",
  "MSG_LOG_ALM_1_6012": "The modbus sub program can not be excuted",
  "MSG_LOG_ALM_1_6013": "Modbus I/O variable get failed.",
  "MSG_LOG_ALM_1_6014": "A Modbus I/O variable with the same name has already been added.",
  "MSG_LOG_ALM_2_1101": "Given tool weight or COG exceeds allowable limit",
  "MSG_LOG_ALM_2_1102": "TCP length or angle exceeds allowable range ",
  "MSG_LOG_ALM_2_1103": "Joint limit setup error: attemped to set joint limit greater than its maximum or excluding current joint angle",
  "MSG_LOG_ALM_2_1104": "The entered TCP length exceeds the range that can be set in this feature.",
  "MSG_LOG_ALM_2_1105": "The estimated value of base tilt angle is smaller than 5 degrees. Both the base tilt and rotation angle do not change",
  "MSG_LOG_ALM_2_1106": "The estimated weight may be incorrect. Re-run the weight estimate with the third axis greater than 30 degrees or less than -30 degrees.",
  "MSG_LOG_ALM_2_1107": "Invalid input value for calculation/configuration of user coordinate",
  "MSG_LOG_ALM_2_1108": "Failed to set new user coordinate because more than 100 user coordinates can not be set",
  "MSG_LOG_ALM_2_1109": "Failed to execute user coordinate functions",
  "MSG_LOG_ALM_2_1110": "Set TCP : {{0}}",
  "MSG_LOG_ALM_2_1111": "Set Tool Weight/CoG : {{0}}",
  "MSG_LOG_ALM_2_1112": "An error occurred while configuring the workpiece weight/CoG.",
  "MSG_LOG_ALM_2_1113": "Set Workpiece Weight./CoG\r\nDetailed Info:: {{0}}",
  "MSG_LOG_ALM_2_1117": "An error occurred while configuring the tool weight.",
  "MSG_LOG_ALM_2_1118": "A notification occurred while configuring the tool weight.\r\nDetailed cause: {{0}}",
  "MSG_LOG_ALM_2_1119": "An error occurred while configuring the deflection compensation.",
  "MSG_LOG_ALM_2_1120": "A notification occurred while configuring the deflection compensation.\r\nDetailed cause: {{0}}",
  "MSG_LOG_ALM_2_1201": "Insufficient via points are provided for given motion (identical consequtive via points shall be ignored)",
  "MSG_LOG_ALM_2_1202": "Motion blend error: movesx, movesj, moveb and move_spiral motions cannot overlap with other motions. Use (m)wait(0) command between the former and other motions.",
  "MSG_LOG_ALM_2_1203": "Motion blending cannot be superposed while another motion blending is being undertaken. Use (m)wait() to adjust starting instance of new motion.",
  "MSG_LOG_ALM_2_1204": "Fail to generate circular trajectory for given via points.",
  "MSG_LOG_ALM_2_1205": "Blending radius error: attempted to set blending radius to a value greater than 50% of the consequtive motion or negative.",
  "MSG_LOG_ALM_2_1206": "Target TCP position exceeds workspace limit (ensure target task position as well as intermediate position is within workspace limit).",
  "MSG_LOG_ALM_2_1207": "Target joint position exceeds user joint limit (ensure target joint position as well as intermediate joint position is within user joint limit).",
  "MSG_LOG_ALM_2_1208": "Target joint speed exceeds user speed limit.",
  "MSG_LOG_ALM_2_1209": "Target task speed exceeds user speed limit.",
  "MSG_LOG_ALM_2_1210": "Errorneous motion axis is given.",
  "MSG_LOG_ALM_2_1211": "Errorneous motion time is given.",
  "MSG_LOG_ALM_2_1212": "Resulting target speed to complete present motion within the given motion duration exceeds user speed limit (adjust motion duration)",
  "MSG_LOG_ALM_2_1213": "Invalid value for setting Alter-motion mode ",
  "MSG_LOG_ALM_2_1214": "Resulting target speed to complete present motion within the given motion duration exceeds user speed limit (motion duration shall be adjusted to meet user speed limit)",
  "MSG_LOG_ALM_2_1215": "An error occurred while using the real-time external control motion command.",
  "MSG_LOG_ALM_2_1216": "A notification occurred while using the real-time external control motion command.\r\nDetailed cause: {{0}}",
  "MSG_LOG_ALM_2_1218": "Invalid periodic motion setting was requested (please check width and period setting)",
  "MSG_LOG_ALM_2_1219": "The Flange z-axis and the Base Frame z-axis are out of the permissible range.",
  "MSG_LOG_ALM_2_1220": "Unsupported coordinate system input.",
  "MSG_LOG_ALM_2_1221": "Converted the target input value of the 4th axis to 0.",
  "MSG_LOG_ALM_2_1222": "Converted the 4th and 5th amp periodic values to 0.",
  "MSG_LOG_ALM_2_1223": "The target point is too distorted to perform the projection.",
  "MSG_LOG_ALM_2_1224": "Unsupported Axis input.",
  "MSG_LOG_ALM_2_1225": "The deviation of the z-axis defined by the set point from the base z-axis exceeds the permissible limit. (max: 5.72958*10^(-5))",
  "MSG_LOG_ALM_2_1226": "Axis alignment has been completed.",
  "MSG_LOG_ALM_2_1301": "Cannot form parallel direction from the three given points or from the given vector",
  "MSG_LOG_ALM_2_1302": "Cannot form alignment direction from the three given points or from the given vector",
  "MSG_LOG_ALM_2_1303": "Failed to reference conveyor corresponding to entered name. Please check the conveyor name",
  "MSG_LOG_ALM_2_1304": "Failed to reference conveyor corresponding to entered ID. Please check the conveyor ID number",
  "MSG_LOG_ALM_2_1305": "During conveyor tracking, the entered relative/absolute mode option for the motion command is not available.",
  "MSG_LOG_ALM_2_1306": "During conveyor tracking, entered command is not available.",
  "MSG_LOG_ALM_2_1307": "Invalid value for setting Conveyor tracking.",
  "MSG_LOG_ALM_2_1308": "Invalid value for Welding Application ",
  "MSG_LOG_ALM_2_1401": "maximum value must be greater than minimum value in check_position_condition",
  "MSG_LOG_ALM_2_1402": "maximum value must be greater than minimum value in check_force_condition",
  "MSG_LOG_ALM_2_1421": "Force control gain input value is out of range.",
  "MSG_LOG_ALM_2_1422": "Invalid force control gain input value.",
  "MSG_LOG_ALM_2_1501": "Failed to initiate automatic estimation of install pose due to inconsistent JTS measure with model-based calculation",
  "MSG_LOG_ALM_2_1502": "Failed to set Protected zone",
  "MSG_LOG_ALM_2_1503": "Failed to set Collision mute zone",
  "MSG_LOG_ALM_2_1504": "Failed to set Tool Orientation Limit Zone",
  "MSG_LOG_ALM_2_1505": "Failed to set Tool shape",
  "MSG_LOG_ALM_2_1506": "Failed to set Robot shape",
  "MSG_LOG_ALM_2_1507": "Fail to set Safe zone",
  "MSG_LOG_ALM_2_1508": "Failed to add new safety zone",
  "MSG_LOG_ALM_2_1509": "Failed to delete existing safety zone",
  "MSG_LOG_ALM_2_1510": "The safety zone(s) that were conflicting with the set global safety limit have been deactivated.",
  "MSG_LOG_ALM_2_1601": "Virtual Fence can only be activated when robot is inside in it.",
  "MSG_LOG_ALM_2_1602": "Current TCP penatrates virtual fence",
  "MSG_LOG_ALM_2_1603": "Target task position penetrates virtual fence : Cylinder",
  "MSG_LOG_ALM_2_1604": "Target task position penetrates virtual fence : Cuboid",
  "MSG_LOG_ALM_2_1605": "Target task position penetrates virtual fence : Polyhedron",
  "MSG_LOG_ALM_2_1903": "Currently not permitted event is attempted",
  "MSG_LOG_ALM_2_1904": "Mathmatic operatoin failed due to abnormal user input.",
  "MSG_LOG_ALM_2_1905": "Fail to Set Nudge configuration (Please check Threshold Force or DelayTime)",
  "MSG_LOG_ALM_2_1906": "Unavailable to activate Nudge Function since this function is disabled, the Robot is moving or is out of Collaborative zone or Crushing prevention zone or Custom zone with collaborative zone option",
  "MSG_LOG_ALM_2_1907": "Reference Coordinate input is not valid",
  "MSG_LOG_ALM_2_1908": "An invalid control command was generated.",
  "MSG_LOG_ALM_2_2301": "The JTS calibration results exceed normal range.",
  "MSG_LOG_ALM_2_2302": "The FTS calibration results exceed normal range.",
  "MSG_LOG_ALM_2_2501": "Current joint position exceeds user limit",
  "MSG_LOG_ALM_2_2502": "Current joint speed exceeds user limit",
  "MSG_LOG_ALM_2_2503": "Joint torque exceeds max value",
  "MSG_LOG_ALM_2_2504": "Current power exceeds user limit",
  "MSG_LOG_ALM_2_2505": "Current external force exceeds user limit",
  "MSG_LOG_ALM_2_2506": "Current momentum exceeds user limit",
  "MSG_LOG_ALM_2_2507": "Current TCP speed exceeds user limit",
  "MSG_LOG_ALM_2_3202": "Fail to reflect alter amount to the motion by internal reason ",
  "MSG_LOG_ALM_2_3203": "Input alter amount is limited to the user&apos;&apos;s threshold (Please check the limit value of enable_alter_motion())",
  "MSG_LOG_ALM_2_3204": "Input alter amount is not reflected for the trajectory motion (eg. movel, movec) finished. (Robot might abruptly stop and cause residual vibration for a while)",
  "MSG_LOG_ALM_2_3205": "Inside of singularity region",
  "MSG_LOG_ALM_2_3206": "Outside of singularity region",
  "MSG_LOG_ALM_2_3207": "Change from virtual recovery mode to normal mode",
  "MSG_LOG_ALM_2_3208": "Change from normal mode to virtual recovery mode",
  "MSG_LOG_ALM_2_3209": "Fail to set palletizing mode",
  "MSG_LOG_ALM_2_3210": "Speed/acceleration auto-mode related notification has occurred.",
  "MSG_LOG_ALM_2_3211": "Speed/acceleration auto-mode related error has occurred.",
  "MSG_LOG_ALM_2_3212": "Adjusted to not exceed the TCP Speed Limit",
  "MSG_LOG_ALM_2_3213": "Constant speed operation is not feasible when the distance between consequtive via points is less than 0.1mm[0.0039in]. Variable speed operation shall be applied automatically.",
  "MSG_LOG_ALM_2_3215": "Jog motion was stopped in order not to exceed Joint Limit",
  "MSG_LOG_ALM_2_3216": "Jog motion was stopped in order not to exceed Workspace Limit",
  "MSG_LOG_ALM_2_3217": "Jog motion was stopped in order not to cause rapid motion near the singular configuration",
  "MSG_LOG_ALM_2_3218": "An error has occurred with the offset input value of the Move along the path button.",
  "MSG_LOG_ALM_2_3219": "The device is not in the location or position of its last task. Please move the robot to where it stopped working and perform End Handguiding action.",
  "MSG_LOG_ALM_2_3301": "Fail to execute Automatic Tool/Weight measurement due to robot joint configuration is near the singular point. Joint motion of axis 2,3 is recommended to avoid singular point",
  "MSG_LOG_ALM_2_3302": "Tracking accuracy could be low due to that speed of conveyor is too high.",
  "MSG_LOG_ALM_2_3303": "Unavailable to complete Sync-In tracking motion because TCP position is too close to Sync Out zone",
  "MSG_LOG_ALM_2_3304": "Conveyor tracking is terminated because of invading SyncOut zone while conveyor tracking.",
  "MSG_LOG_ALM_2_3305": "Unavailable to pause or resume process during conveyor tracking due to a safety reason ",
  "MSG_LOG_ALM_2_3306": "Weaving Function Failure during Welding Application : ",
  "MSG_LOG_ALM_2_3307": "Weld Procedure Failure during Welding Application : ",
  "MSG_LOG_ALM_2_3308": "Weaving Function Informs. during Welding Application : ",
  "MSG_LOG_ALM_2_3309": "Weld Procedure Informs. during Welding Application : ",
  "MSG_LOG_ALM_2_3310": "The DAQ device connection has been lost.",
  "MSG_LOG_ALM_2_3311": "A problem has occurred with the current measurement.",
  "MSG_LOG_ALM_2_3312": "The Arc Sensing function calibration value has exceeded the maximum limit.",
  "MSG_LOG_ALM_2_3403": "Compliance control can be unstable near singular configuration",
  "MSG_LOG_ALM_2_3404": "Fail to execute force_reset function (because of exceeding threshold or unavailable state) ",
  "MSG_LOG_ALM_2_3501": "Joint external torque exceeds reference value",
  "MSG_LOG_ALM_2_3502": "Fail to initiate direct teaching mode due to inconsistent JTS measure with model-based calculation",
  "MSG_LOG_ALM_2_3503": "Joint external torque exceeds reference value when entering compliance ctrl",
  "MSG_LOG_ALM_2_3504": "Joint external torque exceeds reference value when entering force ctrl",
  "MSG_LOG_ALM_2_3505": "JTS measured valure greatly differs from model-based calculation before JTS calibration",
  "MSG_LOG_ALM_2_3506": "Joint external torque exceeds reference value when entering direct teaching ctrl",
  "MSG_LOG_ALM_2_3507": "Abnormal JTS calibration results (scale/offset). Check soundness of JTS.",
  "MSG_LOG_ALM_2_3508": "Fail to return to original Trajectory after RS1-mode stop",
  "MSG_LOG_ALM_2_3509": "Commanded motion can be unstable in the vicinity of singular configuration",
  "MSG_LOG_ALM_2_3510": "Target velocity of a (or some) joint exceeds allowable maximum joint velocity",
  "MSG_LOG_ALM_2_3901": "Calculated value at a location the robot cannot reach or at a force range the robot cannot apply.",
  "MSG_LOG_ALM_2_3905": "Inverse kinematics solution can&apos;&apos;t be obtained.",
  "MSG_LOG_ALM_2_4501": "Fail to complete boot up process due to inconsistent JTS measure with model-based calculation. Check body contact, appropriate tool setting, and JTS failure.",
  "MSG_LOG_ALM_2_4508": "Errorneous JTS value is detected",
  "MSG_LOG_ALM_2_4901": "FTS exceeds allowable limit ",
  "MSG_LOG_ALM_2_5902": "Calculated value exceeds set range.",
  "MSG_LOG_ALM_2_6104": "Stop unavailable during estimation of tool weight info.",
  "MSG_LOG_ALM_2_6301": "JTS calibration procedure has been stopped by internal failure or user request",
  "MSG_LOG_ALM_2_6302": "Install pose measurement procedure has been stopped by internal failure or user request",
  "MSG_LOG_ALM_2_6303": "Tool measurement procedure has been stopped by internal failure or user request",
  "MSG_LOG_ALM_2_6304": "TCP measurement procedure has been stopped by internal failure or user request",
  "MSG_LOG_ALM_2_9001": "STO (Safe Torque Off, removal of motor power) is activated.",
  "MSG_LOG_ALM_2_9002": "SBC (Safe Brake Control, removal of motor power and brake) is activated.",
  "MSG_LOG_ALM_2_9003": "SS1 (Safe Stop 1, deceleration &amp; removal of motor power) is activated",
  "MSG_LOG_ALM_2_9004": "SS2 (Safe Stop 2, deceleration &amp; standstill monitoring)  is activated.",
  "MSG_LOG_ALM_2_9005": "Emergency Stop is activated.",
  "MSG_LOG_ALM_2_9006": "Protective stop is activated.",
  "MSG_LOG_ALM_2_9007": "Standstill status is violated in at least one joint.",
  "MSG_LOG_ALM_2_9008": "Current joint position exceeds user limit in at least one joint.",
  "MSG_LOG_ALM_2_9009": "Joint speed has exceeded user limit in at least one joint.",
  "MSG_LOG_ALM_2_9010": "Joint torque has exceeded user limit in at least one joint.",
  "MSG_LOG_ALM_2_9011": "Collision has been detected.",
  "MSG_LOG_ALM_2_9012": "TCP(Tool Center Point) overstepped the workspace limit.",
  "MSG_LOG_ALM_2_9013": "TCP(Tool Center Point) overstepped user orientation limit.",
  "MSG_LOG_ALM_2_9014": "TCP speed has exceeded user limit.",
  "MSG_LOG_ALM_2_9015": "TCP force has exceeded user limit.",
  "MSG_LOG_ALM_2_9016": "Momentum of the robot arm has exceeded user limit.",
  "MSG_LOG_ALM_2_9017": "Power of the robot arm has exceeded user limit.",
  "MSG_LOG_ALM_2_9018": "Safety related Input or Output discrepancy has occured.",
  "MSG_LOG_ALM_2_9019": "Unavailable to activate Nudge Function since the robot is in/near singular configuration",
  "MSG_LOG_ALM_2_9301": "TCP position reached out of Collaborative zone or Crushing prevention zone or Custom zone with collaborative zone option while executing wait_manual_guide() command",
  "MSG_LOG_ALM_2_9401": "Desired force must be out of the range, -10~10N[-2.2481~2.2481lbf] and -5Nm~5Nm[-3.6878~3.6878lb ft]",
  "MSG_LOG_ALM_3_0": "0",
  "MSG_LOG_ALM_4_1000": "Status good.",
  "MSG_LOG_ALM_4_1001": "Unknown error occurred.",
  "MSG_LOG_ALM_4_1002": "SDO communication error occurred.",
  "MSG_LOG_ALM_4_1003": "Motor Phase Over Current Error",
  "MSG_LOG_ALM_4_1004": "DC-Link Over Voltage Error",
  "MSG_LOG_ALM_4_1005": "DC-Link Under Voltage Error",
  "MSG_LOG_ALM_4_1006": "High Ambient Temperature",
  "MSG_LOG_ALM_4_1007": "Low Ambient Temperature",
  "MSG_LOG_ALM_4_1008": "Control Voltage Error (24V)",
  "MSG_LOG_ALM_4_1009": "Control Voltage Error (5V)",
  "MSG_LOG_ALM_4_1010": "Control Voltage Error (17V)",
  "MSG_LOG_ALM_4_1011": "Brake Voltage Error",
  "MSG_LOG_ALM_4_1012": "Core Voltage 1 Error",
  "MSG_LOG_ALM_4_1013": "Core Voltage 2 Error",
  "MSG_LOG_ALM_4_1014": "Current Sensor Offset Error",
  "MSG_LOG_ALM_4_1015": "Incremental Encoder Error",
  "MSG_LOG_ALM_4_1016": "Absolute Encoder Multi-turn Error",
  "MSG_LOG_ALM_4_1017": "Absolute Encoder CRC Error",
  "MSG_LOG_ALM_4_1018": "Max Speed Error",
  "MSG_LOG_ALM_4_1019": "Software Position Limit Error",
  "MSG_LOG_ALM_4_1020": "Hall Sensor Error 1",
  "MSG_LOG_ALM_4_1021": "Hall Sensor Error 2",
  "MSG_LOG_ALM_4_1022": "Communication Error",
  "MSG_LOG_ALM_4_1023": "Communication Error-Heart Beat",
  "MSG_LOG_ALM_4_1024": "Initial Start Error",
  "MSG_LOG_ALM_4_1025": "Position Following Error",
  "MSG_LOG_ALM_4_1026": "Position Reference Error",
  "MSG_LOG_ALM_4_1027": "STO (Safe Torque Off)",
  "MSG_LOG_ALM_4_1028": "External Fault",
  "MSG_LOG_ALM_4_1029": "Abnormal Joint Torque",
  "MSG_LOG_ALM_4_1030": "Motor Over Load",
  "MSG_LOG_ALM_4_1031": "Inverter Over Current Error (H/W)",
  "MSG_LOG_ALM_4_1032": "Brake Current Error",
  "MSG_LOG_ALM_4_1033": "Position Sensor Index Error 1",
  "MSG_LOG_ALM_4_1034": "Position Sensor Index Error 2",
  "MSG_LOG_ALM_4_1035": "Controller Version Error",
  "MSG_LOG_ALM_4_1036": "Harmonic Drive Type Error",
  "MSG_LOG_ALM_4_1037": "Memory Parameters Error",
  "MSG_LOG_ALM_4_1038": "Cia402 StateMachine Error",
  "MSG_LOG_ALM_4_1039": "Abnormal Torque of the JTS #1",
  "MSG_LOG_ALM_4_1040": "Abnormal Torque of the JTS #2",
  "MSG_LOG_ALM_4_1041": "Large Torque Difference between the JTSs",
  "MSG_LOG_ALM_4_1042": "Excess Torque Variation of the JTS",
  "MSG_LOG_ALM_4_1043": "JTS #1 value does not change.",
  "MSG_LOG_ALM_4_1044": "JTS #2 value does not change.",
  "MSG_LOG_ALM_4_1045": "JTS #1 and JTS #2 have the same value.",
  "MSG_LOG_ALM_4_1046": "Unbalanced Current Error",
  "MSG_LOG_ALM_4_1047": "Module Temperature too High",
  "MSG_LOG_ALM_4_1048": "Module Temperature too low",
  "MSG_LOG_ALM_4_1049": "Incremental Encoder Count Error",
  "MSG_LOG_ALM_4_1050": "Position Error between Encoders",
  "MSG_LOG_ALM_4_1051": "Speed Error between Encoders",
  "MSG_LOG_ALM_4_1052": "JTS Communication Error-Sequence Number",
  "MSG_LOG_ALM_4_1053": "JTS Communication Error-CRC",
  "MSG_LOG_ALM_4_1055": "ABE error bit has occurred.",
  "MSG_LOG_ALM_4_1060": "A decrease in motor efficiency has been detected. Please contact the Service Team.",
  "MSG_LOG_ALM_4_1061": "The movement has been detected in the robot while it is in the OFF state. Please reset the home position.",
  "MSG_LOG_ALM_5_7001": "RS422 communication sequence number error.",
  "MSG_LOG_ALM_5_7002": "RS422 communication CRC32 check error.",
  "MSG_LOG_ALM_5_7003": "RS422 Unknown command receive error.",
  "MSG_LOG_ALM_5_7004": "RS422 communication error occurred.",
  "MSG_LOG_ALM_5_7005": "EtherCAT communication error occurred.",
  "MSG_LOG_ALM_5_7006": "Data exchange request queue between CPUs is full.",
  "MSG_LOG_ALM_5_7007": "Hand guide mode is not allowed.",
  "MSG_LOG_ALM_5_7008": "CPU intercomparison error (Motion Monitoring Result).",
  "MSG_LOG_ALM_5_7009": "Motion algorithm monitoring cycle exceeded.",
  "MSG_LOG_ALM_5_7010": "Emergency input intercomparison does not match.",
  "MSG_LOG_ALM_5_7011": "Emergency input exceeds rated voltage range.",
  "MSG_LOG_ALM_5_7012": "Protective device input intercomparison does not match.",
  "MSG_LOG_ALM_5_7013": "Protective device input exceeds rated voltage range.",
  "MSG_LOG_ALM_5_7014": "Safety output intercomparison does not match.",
  "MSG_LOG_ALM_5_7015": "Safety output output feedback does not match.",
  "MSG_LOG_ALM_5_7016": "Safety input intercomparison does not match.",
  "MSG_LOG_ALM_5_7017": "CPU intercomparison error (System State).",
  "MSG_LOG_ALM_5_7019": "The signal or connection status of the TBSI dedicated safety input is unstable.",
  "MSG_LOG_ALM_5_7020": "Temperature of Inverter board exceeds normal range.",
  "MSG_LOG_ALM_5_7021": "Raw data sequence number error occurred on Inverter board.",
  "MSG_LOG_ALM_5_7022": "Raw data CRC32 check failed on Inverter board.",
  "MSG_LOG_ALM_5_7023": "Joint torque sensor data sequence number error occurred on Inverter board.",
  "MSG_LOG_ALM_5_7024": "Joint torque sensor data CRC32 check failed on Inverter board.",
  "MSG_LOG_ALM_5_7025": "Motion Controller data sequence number error occurred",
  "MSG_LOG_ALM_5_7026": "Motion Controller data CRC32 check failed",
  "MSG_LOG_ALM_5_7027": "Servo On has not been executed properly. Please perform Servo On",
  "MSG_LOG_ALM_5_7028": "Servo on is retrying operation.",
  "MSG_LOG_ALM_5_7030": "Undefined Instruction Exception occurred.",
  "MSG_LOG_ALM_5_7031": "Prefetch Abort Exception occurred.",
  "MSG_LOG_ALM_5_7032": "Data Abort Exception occurred.",
  "MSG_LOG_ALM_5_7040": "DPRAM command queue sequence number error occurred.",
  "MSG_LOG_ALM_5_7041": "DPRAM command queue CRC32 check failed.",
  "MSG_LOG_ALM_5_7042": "DPRAM queue initializing commmand sequence number error occurred.",
  "MSG_LOG_ALM_5_7043": "DPRAM queue initializing commmand CRC32 check failed.",
  "MSG_LOG_ALM_5_7044": "DPRAM I/O data sequence number error occurred.",
  "MSG_LOG_ALM_5_7045": "DPRAM I/O data CRC32 check failed.",
  "MSG_LOG_ALM_5_7046": "DPRAM interrupt command queue is full.",
  "MSG_LOG_ALM_5_7047": "DPRAM interrupt command queue sequence number error occurred.",
  "MSG_LOG_ALM_5_7048": "DPRAM interrupt command queue CRC32 check failed.",
  "MSG_LOG_ALM_5_7049": "RS422 Communication data intercomparison does not match.",
  "MSG_LOG_ALM_5_7050": "STO (Safe Torque Off, removal of motor power) is activated.",
  "MSG_LOG_ALM_5_7051": "RS1 Violation is activated",
  "MSG_LOG_ALM_5_7052": "SS1 (Safe Stop 1, deceleration and removal of motor power) is activated",
  "MSG_LOG_ALM_5_7053": "SS2 (Safe Stop 2, deceleration and standstill monitoring)  is activated.",
  "MSG_LOG_ALM_5_7054": "Emergency Stop is activated.",
  "MSG_LOG_ALM_5_7055": "Protective stop is activated.",
  "MSG_LOG_ALM_5_7056": "Standstill status is violated in at least one joint.",
  "MSG_LOG_ALM_5_7057": "Current joint position exceeds user limit in at least one joint.",
  "MSG_LOG_ALM_5_7058": "Joint speed has exceeded user limit in at least one joint.",
  "MSG_LOG_ALM_5_7059": "Joint torque has exceeded user limit in at least one joint.",
  "MSG_LOG_ALM_5_7060": "Collision has been detected.",
  "MSG_LOG_ALM_5_7061": "TCP(Tool Center Point) overstepped the workspace limit.",
  "MSG_LOG_ALM_5_7062": "TCP(Tool Center Point) overstepped user orientation limit.",
  "MSG_LOG_ALM_5_7063": "TCP speed has exceeded user limit.",
  "MSG_LOG_ALM_5_7064": "TCP force has exceeded user limit.",
  "MSG_LOG_ALM_5_7065": "Momentum of the robot arm has exceeded user limit.",
  "MSG_LOG_ALM_5_7066": "Power of the robot arm has exceeded user limit.",
  "MSG_LOG_ALM_5_7067": "Robot Self Body Collision has been detected.",
  "MSG_LOG_ALM_5_7068": "Protective Zone violation has been detected.",
  "MSG_LOG_ALM_5_7069": "The difference between the Incremental encoder and the Absolute encoder values exceeds limit range.",
  "MSG_LOG_ALM_5_7070": "The difference between the JTS # 1 and # 2 values exceeds limit range.",
  "MSG_LOG_ALM_5_7071": "Sum of three-phase current exceeds reference value",
  "MSG_LOG_ALM_5_7072": "Motor torque value does not match the value converted from three-phase current",
  "MSG_LOG_ALM_5_7073": "Joint position control error exceeds error tolerance.",
  "MSG_LOG_ALM_5_7074": "Unavailable to activate Nudge Function since external force is apllied continually.",
  "MSG_LOG_ALM_5_7075": "Parameterization of workpiece weight/CoG is allowed only when the relevant safety functions are muted.",
  "MSG_LOG_ALM_5_7080": "1.2V voltage of inverter board exceeds normal range.",
  "MSG_LOG_ALM_5_7081": "3.3V voltage of inverter board exceeds normal range.",
  "MSG_LOG_ALM_5_7082": "5.0V voltage of inverter board exceeds normal range.",
  "MSG_LOG_ALM_5_7083": "17V voltage of inverter board exceeds normal range.",
  "MSG_LOG_ALM_5_7084": "24V voltage of inverter board exceeds normal range.",
  "MSG_LOG_ALM_5_7085": "24V logic voltage of inverter board exceeds normal range.",
  "MSG_LOG_ALM_5_7086": "48V voltage of inverter board exceeds normal range.",
  "MSG_LOG_ALM_5_7090": "CPU A(B) detects 24V or greater at CPU B(A).",
  "MSG_LOG_ALM_5_7091": "CPU A(B) detects 6V or greater at CPU B(A).",
  "MSG_LOG_ALM_5_7092": "CPU A(B) detects 5V or greater at CPU B(A).",
  "MSG_LOG_ALM_5_7093": "CPU A(B) detects 3.3V or greater at CPU B(A).",
  "MSG_LOG_ALM_5_7094": "CPU A(B) detects 1.2V or greater at CPU B(A).",
  "MSG_LOG_ALM_5_7095": "12V power fault detected.",
  "MSG_LOG_ALM_5_7096": "5V power fault detected.",
  "MSG_LOG_ALM_5_7097": "3.3V power fault detected.",
  "MSG_LOG_ALM_5_7098": "2.5V power fault detected.",
  "MSG_LOG_ALM_5_7099": "STO output relay fault detected.",
  "MSG_LOG_ALM_5_7100": "EMIF Data Bus fault detected.",
  "MSG_LOG_ALM_5_7101": "EMIF Address Bus fault detected.",
  "MSG_LOG_ALM_5_7102": "Dynamic SRAM Test is failed",
  "MSG_LOG_ALM_5_7103": "SPI2 bus fault detected.",
  "MSG_LOG_ALM_5_7104": "SPI3 bus fault detected.",
  "MSG_LOG_ALM_5_7105": "CPU temperature exceeds normal range.",
  "MSG_LOG_ALM_5_7106": "Board temperature exceeds normal range.",
  "MSG_LOG_ALM_5_7107": "CPU clock fault detected.",
  "MSG_LOG_ALM_5_7108": "Solid state circuit breaker fault (motor power).",
  "MSG_LOG_ALM_5_7109": "Solid state circuit breaker fault (brake power).",
  "MSG_LOG_ALM_5_7110": "Over-voltage occurred on 48V motor voltage.",
  "MSG_LOG_ALM_5_7111": "Under-voltage occurred on 48V motor voltage .",
  "MSG_LOG_ALM_5_7112": "Over-voltage occurred on 24V brake voltage.",
  "MSG_LOG_ALM_5_7113": "Under-voltage occurred on 24V brake voltage.",
  "MSG_LOG_ALM_5_7114": "Under-voltage occurred on precharge voltage.",
  "MSG_LOG_ALM_5_7115": "Over-current occurred on 48V motor voltage.",
  "MSG_LOG_ALM_5_7116": "Over-current occurred on 24V brake voltage.",
  "MSG_LOG_ALM_5_7117": "Over-current occurred on 24V logic voltage.",
  "MSG_LOG_ALM_5_7118": "Over-current occurred on I/O port",
  "MSG_LOG_ALM_5_7119": "Motor FET fault occurred.",
  "MSG_LOG_ALM_5_7120": "Brake FET fault occurred.",
  "MSG_LOG_ALM_5_7121": "Over-current occurred on precharge voltage.",
  "MSG_LOG_ALM_5_7122": "STO realy fulat occurred.",
  "MSG_LOG_ALM_5_7123": "Compare fault of motor current A occurred.",
  "MSG_LOG_ALM_5_7124": "Compare fault of motor current B occurred.",
  "MSG_LOG_ALM_5_7125": "Compare fault of brake voltage A occurred.",
  "MSG_LOG_ALM_5_7126": "Compare fault of brake voltage B occurred.",
  "MSG_LOG_ALM_5_7127": "Compare fault of motro voltage A occurred.",
  "MSG_LOG_ALM_5_7128": "Compare fault of motro voltage B occurred.",
  "MSG_LOG_ALM_5_7129": "Compare fault of brake current occurred.",
  "MSG_LOG_ALM_5_7130": "Watchdog fault occurred.",
  "MSG_LOG_ALM_5_7131": "Under temperature in CPU occurred.",
  "MSG_LOG_ALM_5_7132": "Under temperature in board occurred.",
  "MSG_LOG_ALM_5_7133": "Over temperature in CPU occurred.",
  "MSG_LOG_ALM_5_7134": "Over temperature in board occurred.",
  "MSG_LOG_ALM_5_7135": "ECC fault in CPU SRAM occurred.",
  "MSG_LOG_ALM_5_7136": "ECC fault in CPU flash occurred.",
  "MSG_LOG_ALM_5_7137": "CRC fault in CPU flash occurred.",
  "MSG_LOG_ALM_5_7138": "Compare fault of joint torque sensor occurred.",
  "MSG_LOG_ALM_5_7139": "Compare fault of motion monitoring logic occurred.",
  "MSG_LOG_ALM_5_7140": "Compare fault of encorder occurred.",
  "MSG_LOG_ALM_5_7141": "I/O 5V power fault occurred.",
  "MSG_LOG_ALM_5_7170": "Cannot change safety configuation outside the specified state.",
  "MSG_LOG_ALM_5_7171": "No TCP info with the same name.",
  "MSG_LOG_ALM_5_7172": "No tool info with the same name.",
  "MSG_LOG_ALM_5_7173": "Invalid general range cofiguration.",
  "MSG_LOG_ALM_5_7174": "Invalid joint range cofiguration.",
  "MSG_LOG_ALM_5_7175": "Invalid safety function cofiguration.",
  "MSG_LOG_ALM_5_7176": "Invalid install pose cofiguration.",
  "MSG_LOG_ALM_5_7177": "Invalid Safety I/O cofiguration.",
  "MSG_LOG_ALM_5_7178": "Invalid virtual wall cofiguration.",
  "MSG_LOG_ALM_5_7179": "Invalid safe zone cofiguration.",
  "MSG_LOG_ALM_5_7180": "Invalid safe zone enable cofiguration.",
  "MSG_LOG_ALM_5_7181": "Invalid protected zone cofiguration",
  "MSG_LOG_ALM_5_7182": "Invalid collision mute zone cofiguration",
  "MSG_LOG_ALM_5_7183": "Invalid tool orientation limit zone cofiguration.",
  "MSG_LOG_ALM_5_7184": "Invalid tool shape cofiguration.",
  "MSG_LOG_ALM_5_7185": "Maximum number of tools that can be saved has been exceeded.",
  "MSG_LOG_ALM_5_7186": "Maximum number of TCPs that can be saved has been exceeded.",
  "MSG_LOG_ALM_5_7187": "No Tool Shape info with the same name.",
  "MSG_LOG_ALM_5_7190": "Failed to add new safety zone",
  "MSG_LOG_ALM_5_7191": "Failed to delete existing safety zone",
  "MSG_LOG_ALM_5_7192": "External Remote I/O Control Mode Signal is cleared",
  "MSG_LOG_ALM_5_7193": "The safety zone(s) that were conflicting with the set global safety limit have been deactivated.",
  "MSG_LOG_ALM_5_7240": "Reserved 1",
  "MSG_LOG_ALM_5_7241": "Reserved 2",
  "MSG_LOG_ALM_5_7242": "Reserved 3",
  "MSG_LOG_ALM_5_7243": "Reserved 4",
  "MSG_LOG_ALM_5_7244": "Reserved 5",
  "MSG_LOG_ALM_5_7245": "Reserved 6",
  "MSG_LOG_ALM_5_7246": "Reserved 7",
  "MSG_LOG_ALM_5_7247": "Reserved 8",
  "MSG_LOG_ALM_5_7248": "Reserved 9",
  "MSG_LOG_ALM_6_1001": "Vision Connection is Failed.",
  "MSG_LOG_ALM_6_1002": "TimeOut",
  "MSG_LOG_ALM_6_1003": "Communication Failed",
  "MSG_LOG_ALM_6_1004": "Invalid Data",
  "MSG_LOG_ALM_6_1005": "Invalid Data Length",
  "MSG_LOG_ALM_6_1250": "Time Out : Vision Result Image Capture",
  "MSG_LOG_ALM_6_1350": "Communication Failed : Vision Result Image Capture",
  "MSG_LOG_ALM_6_1450": "Invalid Data : Vision Result Image Capture"
}
